generic_args/__init__.py
generic_args/errors.py
generic_args/generic_args.py
generic_args/get_args.py
generic_args/py.typed
generic_args-0.0.2.dist-info/LICENSE
generic_args-0.0.2.dist-info/WHEEL
generic_args-0.0.2.dist-info/METADATA
generic_args-0.0.2.dist-info/RECORD
