Metadata-Version: 2.1
Name: generic-args
Version: 0.0.2
Summary: Given an instantiated generic class, retrieve the type arguments of itself or its parents.
Home-page: https://github.com/python-platonic/generic-args
License: MIT
Requires-Python: >=3.7,<3.10
Classifier: Development Status :: 3 - Alpha
Classifier: Intended Audience :: Developers
Classifier: License :: OSI Approved :: MIT License
Classifier: Operating System :: OS Independent
Classifier: Programming Language :: Python :: 3
Classifier: Programming Language :: Python :: 3.7
Classifier: Programming Language :: Python :: 3.8
Classifier: Topic :: Software Development :: Libraries :: Python Modules
Requires-Dist: documented (>=0.1.1,<0.2.0)
Requires-Dist: typing_inspect (>=0.6.0,<0.7.0)
Project-URL: Repository, https://github.com/python-platonic/generic-args
